insider_scripts.py
insider_scripts-1.1.0.dist-info/licenses/LICENSE.txt
insider_scripts-1.1.0.dist-info/METADATA
insider_scripts-1.1.0.dist-info/WHEEL
insider_scripts-1.1.0.dist-info/top_level.txt
insider_scripts-1.1.0.dist-info/RECORD
