Metadata-Version: 2.4
Name: insider_scripts
Version: 1.1.0
Summary: Run python scripts from inside a package without relative import error.
Author-email: Sébastien Gachoud <sebastien.gachoud@gmail.com>
Maintainer: Sébastien Gachoud
Maintainer-email: sebastien.gachoud@gmail.com
Requires-Python: >=3.12
License-File: LICENSE.txt
Requires-Dist: requests
Dynamic: license-file
Dynamic: maintainer
Dynamic: maintainer-email
